{"layers.0.self_attn": [0, 1, 2], "layers.1.self_attn": [0, 1, 2], "layers.2.self_attn": [0, 1, 2], "layers.3.self_attn": [0, 1, 2], "layers.4.self_attn": [0, 1, 2], "layers.5.self_attn": [0, 1, 2], "layers.6.self_attn": [0, 1, 2], "layers.7.self_attn": [0, 1, 2], "layers.8.self_attn": [0, 1, 2], "layers.9.self_attn": [0, 1, 2], "layers.10.self_attn": [0, 1, 2], "layers.11.self_attn": [0, 1, 2], "layers.12.self_attn": [0, 1, 2], "layers.13.self_attn": [0, 1, 2], "layers.14.self_attn": [0, 1, 2], "layers.15.self_attn": [0, 1, 2], "layers.16.self_attn": [0, 1, 2], "layers.17.self_attn": [0, 1, 2], "layers.18.self_attn": [0, 1, 2], "layers.19.self_attn": [0, 1, 2], "layers.20.self_attn": [0, 1, 2], "layers.21.self_attn": [0, 1, 2], "layers.22.self_attn": [0, 1, 2], "layers.23.self_attn": [0, 1, 2], "layers.24.self_attn": [0, 1, 2], "layers.25.self_attn": [0, 1, 2], "layers.26.self_attn": [0, 1, 2], "layers.27.self_attn": [0, 1, 2], "layers.28.self_attn": [0, 1, 2], "layers.29.self_attn": [0, 1, 2], "layers.30.self_attn": [0, 1, 2], "layers.31.self_attn": [0, 1, 2]}